git2string/__init__.py
git2string/concatenator.py
git2string/console.py
git2string/file_handler.py
git2string/ignore_handler.py
git2string/main.py
git2string/repo_downloader.py
git2string/stringify.py
git2string/tokenizer.py
tests/__init__.py
tests/conftest.py
tests/test_suite.py
git2string-0.1.5.dist-info/LICENSE
git2string-0.1.5.dist-info/METADATA
git2string-0.1.5.dist-info/WHEEL
git2string-0.1.5.dist-info/entry_points.txt
git2string-0.1.5.dist-info/top_level.txt
git2string-0.1.5.dist-info/RECORD
