Metadata-Version: 2.2
Name: git2string
Version: 0.1.5
Summary: A tool to turn a Git repository into an LLM-friendly prompt
Home-page: https://github.com/hathibelagal-dev/git2string
Author: Ashraff Hathibelagal
Project-URL: Source, https://github.com/hathibelagal-dev/git2string
Project-URL: Tracker, https://github.com/hathibelagal-dev/git2string/issues
Keywords: ai language-models devtools gpt-4 openai llama mistral gemini chatbot
Classifier: Development Status :: 4 - Beta
Classifier: Intended Audience :: Developers
Classifier: Environment :: Console
Classifier: License :: OSI Approved :: Apache Software License
Classifier: Programming Language :: Python :: 3.6
Classifier: Programming Language :: Python :: 3.7
Classifier: Programming Language :: Python :: 3.8
Classifier: Programming Language :: Python :: 3.9
Requires-Python: >=3.6
License-File: LICENSE
Requires-Dist: tqdm
Requires-Dist: tiktoken
Requires-Dist: rich
Requires-Dist: pathspec
Requires-Dist: gitpython
Dynamic: author
Dynamic: classifier
Dynamic: description
Dynamic: description-content-type
Dynamic: home-page
Dynamic: keywords
Dynamic: project-url
Dynamic: requires-dist
Dynamic: requires-python
Dynamic: summary
